LICENSE
MANIFEST.in
README.rst
setup.py
guzzle_sphinx_theme/__init__.py
guzzle_sphinx_theme.egg-info/PKG-INFO
guzzle_sphinx_theme.egg-info/SOURCES.txt
guzzle_sphinx_theme.egg-info/dependency_links.txt
guzzle_sphinx_theme.egg-info/pbr.json
guzzle_sphinx_theme.egg-info/requires.txt
guzzle_sphinx_theme.egg-info/top_level.txt
guzzle_sphinx_theme/guzzle_sphinx_theme/.DS_Store
guzzle_sphinx_theme/guzzle_sphinx_theme/comments.html
guzzle_sphinx_theme/guzzle_sphinx_theme/globaltoc.html
guzzle_sphinx_theme/guzzle_sphinx_theme/layout.html
guzzle_sphinx_theme/guzzle_sphinx_theme/localtoc.html
guzzle_sphinx_theme/guzzle_sphinx_theme/logo-text.html
guzzle_sphinx_theme/guzzle_sphinx_theme/search.html
guzzle_sphinx_theme/guzzle_sphinx_theme/searchbox.html
guzzle_sphinx_theme/guzzle_sphinx_theme/theme.conf
guzzle_sphinx_theme/guzzle_sphinx_theme/static/.DS_Store
guzzle_sphinx_theme/guzzle_sphinx_theme/static/guzzle.css_t
guzzle_sphinx_theme/guzzle_sphinx_theme/static/jquery.js
guzzle_sphinx_theme/guzzle_sphinx_theme/static/jquery.min.map
guzzle_sphinx_theme/guzzle_sphinx_theme/static/css/bootstrap-theme.min.css
guzzle_sphinx_theme/guzzle_sphinx_theme/static/css/bootstrap.min.css
guzzle_sphinx_theme/guzzle_sphinx_theme/static/fonts/glyphicons-halflings-regular.eot
guzzle_sphinx_theme/guzzle_sphinx_theme/static/fonts/glyphicons-halflings-regular.svg
guzzle_sphinx_theme/guzzle_sphinx_theme/static/fonts/glyphicons-halflings-regular.ttf
guzzle_sphinx_theme/guzzle_sphinx_theme/static/fonts/glyphicons-halflings-regular.woff
guzzle_sphinx_theme/guzzle_sphinx_theme/static/fonts/open-sans/stylesheet.css
guzzle_sphinx_theme/guzzle_sphinx_theme/static/fonts/open-sans/fonts/OpenSans-Bold-webfont.eot
guzzle_sphinx_theme/guzzle_sphinx_theme/static/fonts/open-sans/fonts/OpenSans-Bold-webfont.svg
guzzle_sphinx_theme/guzzle_sphinx_theme/static/fonts/open-sans/fonts/OpenSans-Bold-webfont.ttf
guzzle_sphinx_theme/guzzle_sphinx_theme/static/fonts/open-sans/fonts/OpenSans-Bold-webfont.woff
guzzle_sphinx_theme/guzzle_sphinx_theme/static/fonts/open-sans/fonts/OpenSans-BoldItalic-webfont.eot
guzzle_sphinx_theme/guzzle_sphinx_theme/static/fonts/open-sans/fonts/OpenSans-BoldItalic-webfont.svg
