Metadata-Version: 1.1
Name: guzzle_sphinx_theme
Version: 0.7.11
Summary: Sphinx theme used by Guzzle.
Home-page: https://github.com/guzzle/guzzle_sphinx_theme
Author: Michael Dowling
Author-email: mtdowling@gmail.com
License: UNKNOWN
Platform: UNKNOWN
Classifier: Development Status :: 3 - Alpha
Classifier: Intended Audience :: Developers
Classifier: Natural Language :: English
Classifier: License :: OSI Approved :: MIT License
Classifier: Programming Language :: Python
